README.md
setup.cfg
setup.py
bin/surfboard
surfboard/__init__.py
surfboard/dfa.py
surfboard/feature_extraction.py
surfboard/feature_extraction_multiprocessing.py
surfboard/formants.py
surfboard/hnr.py
surfboard/jitters.py
surfboard/misc_components.py
surfboard/shimmers.py
surfboard/sound.py
surfboard/spectrum.py
surfboard/statistics.py
surfboard/utils.py
surfboard.egg-info/PKG-INFO
surfboard.egg-info/SOURCES.txt
surfboard.egg-info/dependency_links.txt
surfboard.egg-info/not-zip-safe
surfboard.egg-info/requires.txt
surfboard.egg-info/top_level.txt